LiveApex/__init__.py
LiveApex/core.py
LiveApex/lobby.py
LiveApex/server.py
LiveApex/translator.py
liveapex-1.2.dist-info/licenses/LICENSE
liveapex-1.2.dist-info/METADATA
liveapex-1.2.dist-info/WHEEL
liveapex-1.2.dist-info/top_level.txt
liveapex-1.2.dist-info/RECORD
