Metadata-Version: 2.4
Name: LiveApex
Version: 1.2
Summary: A Python library for interacting with the Apex Legends LiveAPI.
Author: Catotron
Keywords: apex legends,live api,python,library
Classifier: Development Status :: 5 - Production/Stable
Classifier: Programming Language :: Python :: 3
Classifier: Operating System :: Microsoft :: Windows
Requires-Python: >=3.12
License-File: LICENSE
Requires-Dist: websockets==12.0
Dynamic: author
Dynamic: classifier
Dynamic: description
Dynamic: description-content-type
Dynamic: keywords
Dynamic: license-file
Dynamic: requires-dist
Dynamic: requires-python
Dynamic: summary
